elektron_mcp/__init__.py
elektron_mcp/main.py
elektron_mcp/digitone/__init__.py
elektron_mcp/digitone/config/__init__.py
elektron_mcp/digitone/config/config.py
elektron_mcp/digitone/data/__init__.py
elektron_mcp/digitone/data/amp.py
elektron_mcp/digitone/data/filters.py
elektron_mcp/digitone/data/fm_drum.py
elektron_mcp/digitone/data/fm_tone.py
elektron_mcp/digitone/data/fx.py
elektron_mcp/digitone/data/lfo.py
elektron_mcp/digitone/data/swarmer.py
elektron_mcp/digitone/data/wavetone.py
elektron_mcp/digitone/models/__init__.py
elektron_mcp/digitone/models/models.py
elektron_mcp/digitone/services/__init__.py
elektron_mcp/digitone/services/amp_fx_controller.py
elektron_mcp/digitone/services/base_synth_controller.py
elektron_mcp/digitone/services/filter_controller.py
elektron_mcp/digitone/services/fm_drum_controller.py
elektron_mcp/digitone/services/fm_tone_controller.py
elektron_mcp/digitone/services/lfo_controller.py
elektron_mcp/digitone/services/swarmer_controller.py
elektron_mcp/digitone/services/wavetone_controller.py
elektron_mcp/digitone/utils/__init__.py
elektron_mcp/digitone/utils/parameter_utils.py
elektron_mcp/mcp_server/__init__.py
elektron_mcp/mcp_server/server.py
elektron_mcp/midi/__init__.py
elektron_mcp/midi/digitone_midi.py
elektron_mcp/tools/__init__.py
elektron_mcp/tools/amp_tool.py
elektron_mcp/tools/filter_tool.py
elektron_mcp/tools/fx_tool.py
elektron_mcp/tools/lfo_tool.py
elektron_mcp/tools/wavetone_tool.py
mseep_elektron_mcp-0.2.5.dist-info/METADATA
mseep_elektron_mcp-0.2.5.dist-info/WHEEL
mseep_elektron_mcp-0.2.5.dist-info/entry_points.txt
mseep_elektron_mcp-0.2.5.dist-info/RECORD
